quickselect/__init__.py
quickselect/floyd_rivest.py
quickselect/hints.py
quickselect/hoare.py
quickselect/py.typed
quickselect/core/__init__.py
quickselect/core/utils.py
quickselect-0.2.2.dist-info/LICENSE
quickselect-0.2.2.dist-info/METADATA
quickselect-0.2.2.dist-info/WHEEL
quickselect-0.2.2.dist-info/top_level.txt
quickselect-0.2.2.dist-info/RECORD
