Metadata-Version: 2.1
Name: quickselect
Version: 0.2.2
Summary: Select algorithms implementation.
Home-page: https://github.com/lycantropos/quickselect/
Download-URL: https://github.com/lycantropos/quickselect/archive/master.zip
Author-email: Azat Ibrakov <azatibrakov@gmail.com>
License: MIT License
Classifier: License :: OSI Approved :: MIT License
Classifier: Programming Language :: Python :: 3.8
Classifier: Programming Language :: Python :: 3.9
Classifier: Programming Language :: Python :: 3.10
Classifier: Programming Language :: Python :: 3.11
Classifier: Programming Language :: Python :: 3.12
Classifier: Programming Language :: Python :: Implementation :: CPython
Classifier: Programming Language :: Python :: Implementation :: PyPy
Requires-Python: >=3.8
License-File: LICENSE
Requires-Dist: typing-extensions >=4.10.0
Provides-Extra: docs
Requires-Dist: Sphinx <8.0,>=7.2.6 ; extra == 'docs'
Requires-Dist: sphinx-rtd-theme <3.0,>=2.0.0 ; extra == 'docs'
Provides-Extra: tests
Requires-Dist: hypothesis <7.0,>=6.99.12 ; extra == 'tests'
Requires-Dist: pytest <9.0,>=8.1.1 ; extra == 'tests'
